Workbook

Sheet README
A1: SAP IS-U Meter-to-Cash QA Portfolio
A2: Manual QA portfolio and test pack inspired by SAP IS-U utilities workflows with multi-tab execution tracker structure.
A3: Purpose | B3: Provide reusable sample manual test cases for an event-driven order processing platform covering order creation, payment authorization, inventory reservation, notification handling, resilience, and end-to-end asynchronous flows.
A4: About This Workbook | B4: Open each module sheet and update Status and Notes during execution. Summary KPIs and module counts refresh automatically. Use RTM and Automation Map tabs to show coverage during interviews and portfolio reviews.
A5: This workbook demonstrates a structured QA approach for utilities transformation programmes covering meter reading, device management, billing, invoicing, customer accounts, integrations, resilience, and end-to-end meter-to-cash validation. | B5: These are portfolio-ready sample QA scenarios designed to demonstrate senior-level event-driven testing strategy. Tailor the message broker, payload contract, retry logic, and final-state rules to your target system.
A6: Default status | B6: Not Run
A7: Portfolio Highlights | B7: High
A8: • SAP IS-U style domain coverage: billing, invoicing, meter reading, device management, customer accounts | B8: Backend / Event-Driven Platform QA
A9: • SIT, UAT, regression, integration, and end-to-end validation scenarios | B9: API -> Event Broker -> Payment -> Inventory -> Notification -> Audit/DB
A10: • RTM and automation mapping included for recruiter and interview discussions | B10: Event integrity, idempotency, sequencing, retries, dead-letter handling, eventual consistency, and final-state reconciliation
A11: This is a personal simulation portfolio created to show testing approach and utilities-domain understanding. It does not contain proprietary SAP assets or client data.

Sheet Summary
A1: SAP IS-U Utilities Transformation - Manual Test Case Tracker
A2: Manual QA test suite for a utilities transformation programme using SAP IS-U style meter-to-cash workflows, adapted to the OpenMRS-style multi-tab execution tracker structure.
A4: Workbook Controls
A5: Default Status | B5: Not Run
A6: Default Priority | B6: High
A7: Portfolio Owner | B7: Ramon Tan Jr
A8: Primary Domain | B8: Utilities / SAP IS-U Style QA
A10: Module Coverage
A11: Module | B11: Sheet Name | C11: Total Cases | D11: High Priority | E11: Risk Cases | F11: Automation Candidates
A12: Meter Reading | B12: 10_Meter_Reading | C12: =COUNTA('10_Meter_Reading'!$A:$A)-2 -> 6 | D12: =COUNTIF('10_Meter_Reading'!$H:$H,"High")+COUNTIF('10_Meter_Reading'!$H:$H,"Critical") -> 5 | E12: =COUNTIF('10_Meter_Reading'!$I:$I,"Negative")+COUNTIF('10_Meter_Reading'!$I:$I,"Edge")+COUNTIF('10_Meter_Reading'!$I:$I,"Recovery")+COUNTIF('10_Meter_Reading'!$I:$I,"Security") -> 4 | F12: =COUNTIF('10_Meter_Reading'!$J:$J,"Yes") -> 4
A13: Device Management | B13: 20_Device_Management | C13: =COUNTA('20_Device_Management'!$A:$A)-2 -> 6 | D13: =COUNTIF('20_Device_Management'!$H:$H,"High")+COUNTIF('20_Device_Management'!$H:$H,"Critical") -> 4 | E13: =COUNTIF('20_Device_Management'!$I:$I,"Negative")+COUNTIF('20_Device_Management'!$I:$I,"Edge")+COUNTIF('20_Device_Management'!$I:$I,"Recovery")+COUNTIF('20_Device_Management'!$I:$I,"Security") -> 2 | F13: =COUNTIF('20_Device_Management'!$J:$J,"Yes") -> 3
A14: Billing & Invoicing | B14: 30_Billing_Invoicing | C14: =COUNTA('30_Billing_Invoicing'!$A:$A)-2 -> 6 | D14: =COUNTIF('30_Billing_Invoicing'!$H:$H,"High")+COUNTIF('30_Billing_Invoicing'!$H:$H,"Critical") -> 5 | E14: =COUNTIF('30_Billing_Invoicing'!$I:$I,"Negative")+COUNTIF('30_Billing_Invoicing'!$I:$I,"Edge")+COUNTIF('30_Billing_Invoicing'!$I:$I,"Recovery")+COUNTIF('30_Billing_Invoicing'!$I:$I,"Security") -> 3 | F14: =COUNTIF('30_Billing_Invoicing'!$J:$J,"Yes") -> 4
A15: Customer Accounts | B15: 40_Customer_Accounts | C15: =COUNTA('40_Customer_Accounts'!$A:$A)-2 -> 6 | D15: =COUNTIF('40_Customer_Accounts'!$H:$H,"High")+COUNTIF('40_Customer_Accounts'!$H:$H,"Critical") -> 5 | E15: =COUNTIF('40_Customer_Accounts'!$I:$I,"Negative")+COUNTIF('40_Customer_Accounts'!$I:$I,"Edge")+COUNTIF('40_Customer_Accounts'!$I:$I,"Recovery")+COUNTIF('40_Customer_Accounts'!$I:$I,"Security") -> 1 | F15: =COUNTIF('40_Customer_Accounts'!$J:$J,"Yes") -> 4
A16: Error Handling & Resilience | B16: 50_Error_Handling_Resilience | C16: =COUNTA('50_Error_Handling_Resilience'!$A:$A)-2 -> 5 | D16: =COUNTIF('50_Error_Handling_Resilience'!$H:$H,"High")+COUNTIF('50_Error_Handling_Resilience'!$H:$H,"Critical") -> 4 | E16: =COUNTIF('50_Error_Handling_Resilience'!$I:$I,"Negative")+COUNTIF('50_Error_Handling_Resilience'!$I:$I,"Edge")+COUNTIF('50_Error_Handling_Resilience'!$I:$I,"Recovery")+COUNTIF('50_Error_Handling_Resilience'!$I:$I,"Security") -> 5 | F16: =COUNTIF('50_Error_Handling_Resilience'!$J:$J,"Yes") -> 3
A17: End-to-End Meter-to-Cash | B17: 60_E2E_Meter_to_Cash | C17: =COUNTA('60_E2E_Meter_to_Cash'!$A:$A)-2 -> 6 | D17: =COUNTIF('60_E2E_Meter_to_Cash'!$H:$H,"High")+COUNTIF('60_E2E_Meter_to_Cash'!$H:$H,"Critical") -> 6 | E17: =COUNTIF('60_E2E_Meter_to_Cash'!$I:$I,"Negative")+COUNTIF('60_E2E_Meter_to_Cash'!$I:$I,"Edge")+COUNTIF('60_E2E_Meter_to_Cash'!$I:$I,"Recovery")+COUNTIF('60_E2E_Meter_to_Cash'!$I:$I,"Security") -> 3 | F17: =COUNTIF('60_E2E_Meter_to_Cash'!$J:$J,"Yes") -> 6
A18: Total | C18: =SUM(C12:C17) -> 35 | D18: =SUM(D12:D17) -> 29 | E18: =SUM(E12:E17) -> 18 | F18: =SUM(F12:F17) -> 24
A25: Execution Status
A26: Status | B26: Count | D26: Metric | E26: Value
A27: Not Run | B27: =COUNTIF('10_Meter_Reading'!$K:$K,$A27)+COUNTIF('20_Device_Management'!$K:$K,$A27)+COUNTIF('30_Billing_Invoicing'!$K:$K,$A27)+COUNTIF('40_Customer_Accounts'!$K:$K,$A27)+COUNTIF('50_Error_Handling_Resilience'!$K:$K,$A27)+COUNTIF('60_E2E_Meter_to_Cash'!$K:$K,$A27) -> 35 | D27: Total Test Cases | E27: =C18 -> 35
A28: Pass | B28: =COUNTIF('10_Meter_Reading'!$K:$K,$A28)+COUNTIF('20_Device_Management'!$K:$K,$A28)+COUNTIF('30_Billing_Invoicing'!$K:$K,$A28)+COUNTIF('40_Customer_Accounts'!$K:$K,$A28)+COUNTIF('50_Error_Handling_Resilience'!$K:$K,$A28)+COUNTIF('60_E2E_Meter_to_Cash'!$K:$K,$A28) -> 0 | D28: Executed Cases | E28: =SUM(B28:B30) -> 0
A29: Fail | B29: =COUNTIF('10_Meter_Reading'!$K:$K,$A29)+COUNTIF('20_Device_Management'!$K:$K,$A29)+COUNTIF('30_Billing_Invoicing'!$K:$K,$A29)+COUNTIF('40_Customer_Accounts'!$K:$K,$A29)+COUNTIF('50_Error_Handling_Resilience'!$K:$K,$A29)+COUNTIF('60_E2E_Meter_to_Cash'!$K:$K,$A29) -> 0 | D29: Execution % | E29: =IF(E27=0,0,E28/E27) -> 0
A30: Blocked | B30: =COUNTIF('10_Meter_Reading'!$K:$K,$A30)+COUNTIF('20_Device_Management'!$K:$K,$A30)+COUNTIF('30_Billing_Invoicing'!$K:$K,$A30)+COUNTIF('40_Customer_Accounts'!$K:$K,$A30)+COUNTIF('50_Error_Handling_Resilience'!$K:$K,$A30)+COUNTIF('60_E2E_Meter_to_Cash'!$K:$K,$A30) -> 0 | D30: Pass Rate | E30: =IF(E28=0,0,B28/E28) -> 0
D31: Fail Rate | E31: =IF(E28=0,0,B29/E28) -> 0

Sheet 10_Meter_Reading
A1: Update the Status and Notes columns during execution. Summary KPIs and counts refresh automatically.
A2: TC_ID | B2: Module | C2: Scenario | D2: Preconditions | E2: Steps | F2: Test Data | G2: Expected Result | H2: Priority | I2: Type | J2: Automation Candidate | K2: Status | L2: Notes
A3: MR-001 | B3: Meter Reading | C3: Valid interval meter reading is accepted and stored for billing | D3: Meter is active and scheduled read window is open | E3: 1. Submit valid reading for active meter 2. Review response and stored read record 3. Confirm read timestamp and source channel | F3: meterId=MTR-1001; readValue=1250.45 kWh; readType=Actual | G3: Reading is accepted, stored successfully, and marked eligible for downstream billing validation | H3: Critical | I3: Positive | J3: Yes | K3: Not Run | L3: Core happy path
A4: MR-002 | B4: Meter Reading | C4: Estimated read is flagged correctly when actual read is unavailable | D4: Meter is active and estimation rule is configured | E4: 1. Trigger estimated read generation 2. Review read classification and audit trail | F4: meterId=MTR-1002; estimated read | G4: System records estimated read with correct indicator and audit details | H4: High | I4: Edge | J4: No | K4: Not Run | L4: Estimation handling
A5: MR-003 | B5: Meter Reading | C5: Duplicate meter reading does not create duplicate consumption records | D5: Idempotency or duplicate detection rule is available | E5: 1. Submit same read twice for same meter/date 2. Review stored records | F5: same meterId/date/value | G5: System prevents duplicate consumption record creation and logs duplicate attempt | H5: Critical | I5: Edge | J5: Yes | K5: Not Run | L5: Idempotency control
A6: MR-004 | B6: Meter Reading | C6: Out-of-range reading is rejected or sent for exception handling | D6: Validation rules are configured | E6: 1. Submit abnormally high read 2. Review validation response and exception queue | F6: meterId=MTR-1003; readValue=999999 | G6: Reading is rejected or routed to exception handling without affecting billable data | H6: High | I6: Negative | J6: Yes | K6: Not Run | L6: Validation guardrail
A7: MR-005 | B7: Meter Reading | C7: Missing required meter identifier prevents read acceptance | D7: API or upload channel is available | E7: 1. Submit read without meterId 2. Review response | F7: readValue=145.00 without meterId | G7: Request is rejected with validation error and no billing record is created | H7: High | I7: Negative | J7: Yes | K7: Not Run | L7: Mandatory field validation
A8: MR-006 | B8: Meter Reading | C8: Read audit trail preserves source, timestamp, and status | D8: Audit/log storage is available | E8: 1. Submit valid and invalid reads 2. Review audit entries | F8: actual and invalid samples | G8: Audit captures meterId, source, read type, validation result, and timestamps for traceability | H8: Medium | I8: Positive | J8: No | K8: Not Run | L8: Operational visibility

Sheet 20_Device_Management
A1: Update the Status and Notes columns during execution. Summary KPIs and counts refresh automatically.
A2: TC_ID | B2: Module | C2: Scenario | D2: Preconditions | E2: Steps | F2: Test Data | G2: Expected Result | H2: Priority | I2: Type | J2: Automation Candidate | K2: Status | L2: Notes
A3: DM-001 | B3: Device Management | C3: Device installation update is reflected correctly in customer-premise data | D3: Device master and premise records exist | E3: 1. Register installed meter device 2. Review device-premise association | F3: deviceId=DEV-2001; premiseId=PRM-001 | G3: Device is linked correctly to premise and available for future reads and billing | H3: High | I3: Positive | J3: No | K3: Not Run | L3: Master data flow
A4: DM-002 | B4: Device Management | C4: Meter exchange preserves continuity of billing-relevant data | D4: Old and new devices are available | E4: 1. Perform meter exchange 2. Review final device state and read continuity | F4: oldDevice=DEV-OLD; newDevice=DEV-NEW | G4: Old device is retired, new device is active, and continuity data is preserved for billing | H4: Critical | I4: Positive | J4: Yes | K4: Not Run | L4: Common utilities scenario
A5: DM-003 | B5: Device Management | C5: Inactive or removed device cannot accept new billable reads | D5: Inactive device record exists | E5: 1. Submit read for removed device 2. Review result | F5: deviceStatus=Removed | G5: System rejects read or flags it as invalid for billing processing | H5: High | I5: Negative | J5: Yes | K5: Not Run | L5: Lifecycle validation
A6: DM-004 | B6: Device Management | C6: Device status change is propagated to downstream systems/interfaces | D6: Integration to downstream systems is enabled | E6: 1. Update device status 2. Check interface messages/logs | F6: device status change Active->Inactive | G6: Status update is reflected consistently across integrated systems without mismatch | H6: High | I6: Positive | J6: Yes | K6: Not Run | L6: Integration coverage
A7: DM-005 | B7: Device Management | C7: Unsupported device attributes are validated before save | D7: Device master maintenance is available | E7: 1. Submit invalid device configuration 2. Review validation | F7: unsupported register/profile setup | G7: System prevents invalid device configuration from being saved | H7: Medium | I7: Negative | J7: No | K7: Not Run | L7: Configuration control
A8: DM-006 | B8: Device Management | C8: Device audit trail captures install, exchange, and status events | D8: Audit/log storage is enabled | E8: 1. Perform install/exchange/status change 2. Review logs | F8: install + exchange + status samples | G8: Audit history preserves who changed the device, when, and what action was taken | H8: Medium | I8: Positive | J8: No | K8: Not Run | L8: Traceability

Sheet 30_Billing_Invoicing
A1: Update the Status and Notes columns during execution. Summary KPIs and counts refresh automatically.
A2: TC_ID | B2: Module | C2: Scenario | D2: Preconditions | E2: Steps | F2: Test Data | G2: Expected Result | H2: Priority | I2: Type | J2: Automation Candidate | K2: Status | L2: Notes
A3: BI-001 | B3: Billing & Invoicing | C3: Valid consumption is billed correctly using active tariff | D3: Billable reads and tariff are available | E3: 1. Trigger billing for active account 2. Review bill line items and total | F3: accountId=ACC-3001; consumption=350 kWh; tariff=Residential-A | G3: Bill is calculated correctly with expected consumption charges, taxes, and total amount | H3: Critical | I3: Positive | J3: Yes | K3: Not Run | L3: Core happy path
A4: BI-002 | B4: Billing & Invoicing | C4: Zero consumption applies minimum charge rules correctly | D4: Minimum charge rule is configured | E4: 1. Trigger billing for zero usage account 2. Review billed amount | F4: consumption=0 kWh | G4: System applies configured minimum charge or zero-bill rule correctly | H4: High | I4: Edge | J4: Yes | K4: Not Run | L4: Boundary scenario
A5: BI-003 | B5: Billing & Invoicing | C5: Backdated adjustment rebills the account correctly without duplicate invoicing | D5: Rebilling scenario is enabled | E5: 1. Post corrected read 2. Run rebill 3. Review previous and adjusted invoice records | F5: corrected read for prior period | G5: Rebill adjusts financial result accurately and preserves audit history without duplicate final invoice | H5: Critical | I5: Recovery | J5: Yes | K5: Not Run | L5: Billing correction
A6: BI-004 | B6: Billing & Invoicing | C6: Invalid tariff assignment prevents incorrect bill calculation | D6: Account exists with bad tariff setup | E6: 1. Trigger billing with invalid tariff 2. Review errors and output | F6: tariffCode=INVALID | G6: Billing run fails safely or routes to exception handling without generating incorrect invoice | H6: High | I6: Negative | J6: Yes | K6: Not Run | L6: Financial control
A7: BI-005 | B7: Billing & Invoicing | C7: Invoice output contains correct account, period, charges, tax, and due date | D7: Invoice generation template is configured | E7: 1. Generate invoice 2. Compare output fields with expected billing data | F7: valid bill document | G7: Invoice displays correct customer/account details, billing period, charges, taxes, and due date | H7: High | I7: Positive | J7: No | K7: Not Run | L7: Output validation
A8: BI-006 | B8: Billing & Invoicing | C8: Billing audit trail supports reconciliation between reads, bill document, and invoice | D8: Billing logs/tables are available | E8: 1. Run standard and error scenarios 2. Review linkage across billing artifacts | F8: happy path + invalid tariff | G8: Billing artifacts remain traceable from source read through bill document and invoice | H8: Medium | I8: Positive | J8: No | K8: Not Run | L8: Reconciliation support

Sheet 40_Customer_Accounts
A1: Update the Status and Notes columns during execution. Summary KPIs and counts refresh automatically.
A2: TC_ID | B2: Module | C2: Scenario | D2: Preconditions | E2: Steps | F2: Test Data | G2: Expected Result | H2: Priority | I2: Type | J2: Automation Candidate | K2: Status | L2: Notes
A3: CA-001 | B3: Customer Accounts | C3: New customer account is created with valid premise and contract data | D3: Customer creation process is available | E3: 1. Create new account and service contract 2. Review master data | F3: customerId=CUST-4001; premiseId=PRM-001 | G3: Customer account, contract, and service association are created successfully | H3: High | I3: Positive | J3: No | K3: Not Run | L3: Account setup
A4: CA-002 | B4: Customer Accounts | C4: Move-in process starts billing responsibility on correct date | D4: Move-in scenario is configured | E4: 1. Process move-in 2. Review contract dates and billing start | F4: moveInDate=2026-04-01 | G4: Billing responsibility begins on correct effective date without overlap | H4: Critical | I4: Positive | J4: Yes | K4: Not Run | L4: Meter-to-cash lifecycle
A5: CA-003 | B5: Customer Accounts | C5: Move-out process ends billing correctly and prevents future charges | D5: Move-out scenario is configured | E5: 1. Process move-out 2. Review final bill eligibility and contract status | F5: moveOutDate=2026-04-15 | G5: Account is closed or updated correctly and no further regular charges accrue after move-out | H5: Critical | I5: Positive | J5: Yes | K5: Not Run | L5: Customer lifecycle
A6: CA-004 | B6: Customer Accounts | C6: Account with invalid premise linkage is prevented from billing setup | D6: Validation rules exist | E6: 1. Create account with invalid premise 2. Review result | F6: premiseId invalid | G6: System rejects invalid premise linkage before billing setup completes | H6: High | I6: Negative | J6: Yes | K6: Not Run | L6: Master data validation
A7: CA-005 | B7: Customer Accounts | C7: Payment posting updates outstanding balance correctly | D7: Open invoice exists | E7: 1. Post payment 2. Review account balance and clearing status | F7: invoice=INV-4001; payment=150.00 | G7: Outstanding balance is reduced correctly and account reflects accurate payment status | H7: High | I7: Positive | J7: Yes | K7: Not Run | L7: Financial reconciliation
A8: CA-006 | B8: Customer Accounts | C8: Customer communication preferences flow to billing and notification outputs | D8: Communication preferences are maintained | E8: 1. Update delivery preference 2. Generate invoice/notification | F8: email delivery preference | G8: System uses stored communication preference consistently in customer-facing outputs | H8: Medium | I8: Positive | J8: No | K8: Not Run | L8: Customer experience

Sheet 50_Error_Handling_Resilience
A1: Update the Status and Notes columns during execution. Summary KPIs and counts refresh automatically.
A2: TC_ID | B2: Module | C2: Scenario | D2: Preconditions | E2: Steps | F2: Test Data | G2: Expected Result | H2: Priority | I2: Type | J2: Automation Candidate | K2: Status | L2: Notes
A3: ERR-001 | B3: Error Handling & Resilience | C3: Malformed inbound meter data is routed to exception handling without corrupting billable data | D3: Exception handling path is configured | E3: 1. Submit malformed meter payload 2. Review logs/exception queue | F3: bad JSON / invalid datatype | G3: Invalid payload is isolated safely and valid billing data remains unaffected | H3: Critical | I3: Negative | J3: Yes | K3: Not Run | L3: Advanced scenario
A4: ERR-002 | B4: Error Handling & Resilience | C4: Partial integration outage is detected and retried without duplicate final billing state | D4: Retry logic exists for external dependency | E4: 1. Simulate temporary interface timeout 2. Allow retry 3. Review final state | F4: temporary timeout during billing interface | G4: Retry succeeds or fails cleanly without duplicate bills or corrupted account state | H4: Critical | I4: Recovery | J4: Yes | K4: Not Run | L4: Resilience control
A5: ERR-003 | B5: Error Handling & Resilience | C5: Data migration load rejects incomplete customer or device records | D5: Migration validation rules are defined | E5: 1. Load incomplete migration file 2. Review validation results | F5: missing contract/device mapping | G5: Invalid records are rejected or flagged for correction before cutover | H5: High | I5: Negative | J5: Yes | K5: Not Run | L5: Migration quality
A6: ERR-004 | B6: Error Handling & Resilience | C6: Cutover reconciliation identifies mismatched balances between legacy and target systems | D6: Cutover report is available | E6: 1. Compare legacy and target account balances 2. Review exceptions | F6: sample legacy vs target balances | G6: Mismatches are highlighted clearly for remediation before go-live | H6: High | I6: Recovery | J6: No | K6: Not Run | L6: Go-live support
A7: ERR-005 | B7: Error Handling & Resilience | C7: Batch billing delay is detected within monitoring threshold | D7: Monitoring or SLA threshold is defined | E7: 1. Delay billing batch processing 2. Review alert/monitoring output | F7: delayed billing job | G7: Delay is surfaced within expected monitoring window and operational teams can respond | H7: Medium | I7: Edge | J7: No | K7: Not Run | L7: Operational monitoring

Sheet 60_E2E_Meter_to_Cash
A1: Update the Status and Notes columns during execution. Summary KPIs and counts refresh automatically.
A2: TC_ID | B2: Module | C2: Scenario | D2: Preconditions | E2: Steps | F2: Test Data | G2: Expected Result | H2: Priority | I2: Type | J2: Automation Candidate | K2: Status | L2: Notes
A3: E2E-001 | B3: End-to-End Meter-to-Cash | C3: Happy path completes from meter read to posted invoice and customer balance | D3: All core services and master data are available | E3: 1. Capture valid read 2. Validate bill creation 3. Generate invoice 4. Review customer account balance | F3: valid residential account | G3: Meter read, billing, invoice, and account balance are processed successfully with consistent data | H3: Critical | I3: Positive | J3: Yes | K3: Not Run | L3: Showcase scenario
A4: E2E-002 | B4: End-to-End Meter-to-Cash | C4: Invalid read prevents downstream bill generation and invoice output | D4: Read validation scenario is available | E4: 1. Submit invalid read 2. Review downstream artifacts | F4: out-of-range read | G4: No incorrect bill or invoice is created and exception is recorded clearly | H4: Critical | I4: Negative | J4: Yes | K4: Not Run | L4: Critical control
A5: E2E-003 | B5: End-to-End Meter-to-Cash | C5: Meter exchange before billing maintains correct consumption continuity and bill outcome | D5: Meter exchange scenario is available | E5: 1. Exchange meter mid-cycle 2. Trigger billing 3. Review invoice | F5: old/new meter mid-cycle | G5: Consumption continuity is maintained correctly and billing reflects valid combined usage | H5: Critical | I5: Edge | J5: Yes | K5: Not Run | L5: Real-world utilities case
A6: E2E-004 | B6: End-to-End Meter-to-Cash | C6: Move-out final bill is generated correctly with accurate account closure state | D6: Move-out and final bill flow is configured | E6: 1. Process move-out 2. Generate final bill 3. Review account status | F6: moveOutDate within billing period | G6: Final bill is accurate and customer account reaches correct closure or final-state status | H6: High | I6: Positive | J6: Yes | K6: Not Run | L6: Lifecycle coverage
A7: E2E-005 | B7: End-to-End Meter-to-Cash | C7: Data reconciliation confirms consistency between source reads, billing documents, invoices, and balances | D7: Audit/reporting tables are available | E7: 1. Run success and error scenarios 2. Compare artifacts across stages | F7: mixed scenarios | G7: Source reads, bill documents, invoice values, and account balances reconcile for each account | H7: Critical | I7: Positive | J7: Yes | K7: Not Run | L7: Data reconciliation
A8: E2E-006 | B8: End-to-End Meter-to-Cash | C8: Cutover sample data behaves correctly after go-live smoke validation | D8: Migrated sample records are available | E8: 1. Select migrated accounts 2. Run post-go-live smoke checks | F8: sample migrated accounts | G8: Migrated accounts can read, bill, invoice, and display balances correctly after cutover | H8: High | I8: Recovery | J8: Yes | K8: Not Run | L8: Go-live readiness

Sheet 70_RTM
A1: Traceability view linking SAP IS-U style utilities requirements to manual test coverage. Use this sheet in interviews to show structured QA thinking, domain mapping, and coverage.
A2: REQ_ID | B2: Requirement Area | C2: Requirement Description | D2: Linked Test Cases | E2: Priority | F2: Coverage Status | G2: Notes | H2: Owner | I2: Reviewed
A3: REQ-001 | B3: Meter Reading | C3: System must accept valid reads, reject invalid reads, and preserve read auditability | D3: MR-001, MR-004, MR-005, MR-006, E2E-001, E2E-002 | E3: Critical | F3: Covered | G3: Includes intake validation and traceability | H3: QA | I3: Yes
A4: REQ-002 | B4: Device Management | C4: Device lifecycle changes must maintain valid premise linkage and billing continuity | D4: DM-001, DM-002, DM-003, DM-004, E2E-003 | E4: Critical | F4: Covered | G4: Covers installation, exchange, and downstream propagation | H4: QA | I4: Yes
A5: REQ-003 | B5: Billing & Invoicing | C5: Billing must calculate correct charges and prevent incorrect invoice generation on invalid setup | D5: BI-001, BI-002, BI-003, BI-004, BI-005, BI-006 | E5: Critical | F5: Covered | G5: Financial integrity and rebilling included | H5: QA | I5: Yes
A6: REQ-004 | B6: Customer Accounts | C6: Customer lifecycle events must drive correct billing start, stop, and payment balance behavior | D6: CA-001, CA-002, CA-003, CA-004, CA-005, CA-006, E2E-004 | E6: High | F6: Covered | G6: Account setup to closure lifecycle | H6: QA | I6: Yes
A7: REQ-005 | B7: Resilience & Migration | C7: System must isolate bad data, survive outages, and support cutover/migration validation | D7: ERR-001, ERR-002, ERR-003, ERR-004, ERR-005, E2E-006 | E7: Critical | F7: Covered | G7: Strong interview talking point | H7: QA | I7: Yes
A8: REQ-006 | B8: End-to-End Meter-to-Cash | C8: Source reads, bills, invoices, and balances must reconcile across the full workflow | D8: E2E-001, E2E-005 | E8: Critical | F8: Covered | G8: Core meter-to-cash value chain | H8: QA | I8: Yes

Sheet 80_Automation_Map
A1: Automation planning view showing which SAP IS-U style utilities scenarios are best candidates for API, integration, data validation, and end-to-end automation.
A2: TC_ID | B2: Scenario | C2: Automation Layer | D2: Recommended Tool | E2: Priority | F2: Why Automate | G2: Status | H2: Notes
A3: MR-001 | B3: Valid interval meter reading is accepted and stored | C3: API + Data | D3: Postman + Node.js/Jest | E3: Critical | F3: Core read intake and data quality validation | G3: Planned | H3: Smoke candidate
A4: MR-003 | B4: Duplicate meter reading does not create duplicate records | C4: Integration | D4: Node.js/Jest + fixture replay | E4: Critical | F4: Demonstrates idempotency and financial risk control | G4: Planned | H4: High-value scenario
A5: DM-002 | B5: Meter exchange preserves continuity of billing data | C5: Integration | D5: Playwright/API hybrid or Node.js/Jest | E5: Critical | F5: Strong utilities-domain showcase | G5: Planned | H5: Complex real-world case
A6: BI-001 | B6: Valid consumption is billed correctly using active tariff | C6: API + Data Validation | D6: Postman + CSV comparison script | E6: Critical | F6: Core financial calculation path | G6: Planned | H6: Billing regression
A7: BI-003 | B7: Backdated adjustment rebills correctly | C7: Integration + Data | D7: Node.js/Jest + reconciliation script | E7: Critical | F7: Shows rebill and audit understanding | G7: Planned | H7: Advanced scenario
A8: CA-005 | B8: Payment posting updates outstanding balance | C8: API + Data | D8: Postman + SQL/CSV comparison | E8: High | F8: Important reconciliation control | G8: Planned | H8: Customer account accuracy
A9: E2E-001 | B9: Happy path completes from meter read to posted invoice | C9: End-to-End | D9: Playwright/API hybrid + validation script | E9: Critical | F9: Strongest recruiter demo of meter-to-cash understanding | G9: Planned | H9: Top portfolio scenario
A10: E2E-006 | B10: Migrated sample data behaves correctly after go-live smoke validation | C10: Smoke / Cutover | D10: Postman + checklist automation | E10: High | F10: Supports go-live and cutover conversations | G10: Planned | H10: Programme delivery focus
